unifex/__init__.py
unifex/cli.py
unifex/llm_factory.py
unifex/text_factory.py
unifex/base/__init__.py
unifex/base/base.py
unifex/base/coordinates.py
unifex/base/geometry.py
unifex/base/image_loader.py
unifex/base/models.py
unifex/llm/__init__.py
unifex/llm/models.py
unifex/llm/adapters/__init__.py
unifex/llm/adapters/image_encoder.py
unifex/llm/extractors/__init__.py
unifex/llm/extractors/anthropic.py
unifex/llm/extractors/azure_openai.py
unifex/llm/extractors/google.py
unifex/llm/extractors/openai.py
unifex/ocr/__init__.py
unifex/ocr/adapters/__init__.py
unifex/ocr/adapters/azure_di.py
unifex/ocr/adapters/easy_ocr.py
unifex/ocr/adapters/google_docai.py
unifex/ocr/adapters/paddle_ocr.py
unifex/ocr/adapters/tesseract_ocr.py
unifex/ocr/extractors/__init__.py
unifex/ocr/extractors/azure_di.py
unifex/ocr/extractors/easy_ocr.py
unifex/ocr/extractors/google_docai.py
unifex/ocr/extractors/paddle_ocr.py
unifex/ocr/extractors/tesseract_ocr.py
unifex/pdf/__init__.py
unifex/pdf/character_mergers.py
unifex/pdf/pdf.py
unifex-0.1.1.dist-info/METADATA
unifex-0.1.1.dist-info/WHEEL
unifex-0.1.1.dist-info/licenses/LICENSE
unifex-0.1.1.dist-info/RECORD
