Metadata-Version: 2.4
Name: unifex
Version: 0.1.1
Summary: Unified extraction library for PDF, OCR, and LLM-based document processing
Project-URL: Homepage, https://aptakhin.name/unifex/
Project-URL: Documentation, https://aptakhin.name/unifex/
Project-URL: Repository, https://github.com/aptakhin/unifex
Author-email: SL team <alex.ptakhin@prestatech.com>
License: BSD-3-Clause
License-File: LICENSE
Requires-Python: <4,>=3.11
Requires-Dist: numpy>=1.21
Requires-Dist: pillow>=9.0
Requires-Dist: pydantic>=1.0
Provides-Extra: all
Requires-Dist: anthropic>=0.20; extra == 'all'
Requires-Dist: azure-ai-documentintelligence>=1.0; extra == 'all'
Requires-Dist: easyocr>=1.4; extra == 'all'
Requires-Dist: google-cloud-documentai>=3.0; extra == 'all'
Requires-Dist: google-genai>=1.0; extra == 'all'
Requires-Dist: instructor>=1.0; extra == 'all'
Requires-Dist: jsonref>=1.1.0; extra == 'all'
Requires-Dist: openai>=1.0; extra == 'all'
Requires-Dist: paddleocr>=2.9; extra == 'all'
Requires-Dist: paddlepaddle>=2.6; extra == 'all'
Requires-Dist: pypdfium2>=4.0; extra == 'all'
Requires-Dist: pytesseract>=0.3.8; extra == 'all'
Requires-Dist: tabula-py>=2.0; extra == 'all'
Provides-Extra: azure
Requires-Dist: azure-ai-documentintelligence>=1.0; extra == 'azure'
Provides-Extra: easyocr
Requires-Dist: easyocr>=1.4; extra == 'easyocr'
Provides-Extra: google
Requires-Dist: google-cloud-documentai>=3.0; extra == 'google'
Provides-Extra: llm-all
Requires-Dist: anthropic>=0.20; extra == 'llm-all'
Requires-Dist: google-genai>=1.0; extra == 'llm-all'
Requires-Dist: instructor>=1.0; extra == 'llm-all'
Requires-Dist: jsonref>=1.1.0; extra == 'llm-all'
Requires-Dist: openai>=1.0; extra == 'llm-all'
Provides-Extra: llm-anthropic
Requires-Dist: anthropic>=0.20; extra == 'llm-anthropic'
Requires-Dist: instructor>=1.0; extra == 'llm-anthropic'
Provides-Extra: llm-google
Requires-Dist: google-genai>=1.0; extra == 'llm-google'
Requires-Dist: instructor>=1.0; extra == 'llm-google'
Requires-Dist: jsonref>=1.1.0; extra == 'llm-google'
Provides-Extra: llm-openai
Requires-Dist: instructor>=1.0; extra == 'llm-openai'
Requires-Dist: openai>=1.0; extra == 'llm-openai'
Provides-Extra: paddle
Requires-Dist: paddleocr>=2.9; extra == 'paddle'
Requires-Dist: paddlepaddle>=2.6; extra == 'paddle'
Provides-Extra: pdf
Requires-Dist: pypdfium2>=4.0; extra == 'pdf'
Provides-Extra: tables
Requires-Dist: tabula-py>=2.0; extra == 'tables'
Provides-Extra: tesseract
Requires-Dist: pytesseract>=0.3.8; extra == 'tesseract'
